EasyTkValidations/Validations.py
EasyTkValidations/__init__.py
EasyTkValidations-0.0.3.dist-info/LICENSE.txt
EasyTkValidations-0.0.3.dist-info/METADATA
EasyTkValidations-0.0.3.dist-info/WHEEL
EasyTkValidations-0.0.3.dist-info/top_level.txt
EasyTkValidations-0.0.3.dist-info/RECORD
