Metadata-Version: 2.1
Name: EasyTkValidations
Version: 0.0.3
Summary: To Make Easy Tkinter Entry Validations
Author: DKVG
Author-email: gadellidk@gmail.com
Keywords: Validations EntryValidations TkValidations EasyTk EasyValidations EasyTkValidations
Classifier: Programming Language :: Python :: 3
Classifier: License :: OSI Approved :: MIT License
Classifier: Operating System :: OS Independent
Requires-Python: >=3.9
License-File: LICENSE.txt
